mlstelemetry/LokiWrapper.py
mlstelemetry/MLSTelemetry.py
mlstelemetry/MetricsReceiver.py
mlstelemetry/PrometheusWrapper.py
mlstelemetry/__init__.py
mlstelemetry-0.3.2.dist-info/licenses/LICENSE
mlstelemetry-0.3.2.dist-info/licenses/NOTICE
mlstelemetry-0.3.2.dist-info/METADATA
mlstelemetry-0.3.2.dist-info/WHEEL
mlstelemetry-0.3.2.dist-info/top_level.txt
mlstelemetry-0.3.2.dist-info/RECORD
