Metadata-Version: 2.4
Name: mlstelemetry
Version: 0.3.2
Summary: A library that wraps the OpenTelemetry Python SDK.
Author: MLSysOps Project Consortium
Author-email: info@mlsysops.eu
License: Apache License 2.0
Classifier: Development Status :: 3 - Alpha
Classifier: Intended Audience :: Developers
Classifier: Programming Language :: Python :: 3
Classifier: Programming Language :: Python :: 3.10
License-File: LICENSE
License-File: NOTICE
Provides-Extra: dev
Provides-Extra: build
Requires-Dist: cachetools; extra == "build"
Requires-Dist: opentelemetry-exporter-otlp; extra == "build"
Requires-Dist: opentelemetry-exporter-otlp-proto-common; extra == "build"
Requires-Dist: opentelemetry-exporter-otlp-proto-grpc; extra == "build"
Requires-Dist: opentelemetry-api; extra == "build"
Requires-Dist: opentelemetry-exporter-otlp-proto-http; extra == "build"
Requires-Dist: opentelemetry-proto; extra == "build"
Requires-Dist: opentelemetry-sdk; extra == "build"
Requires-Dist: opentelemetry-semantic-conventions; extra == "build"
Requires-Dist: prometheus_client; extra == "build"
Requires-Dist: asyncio; extra == "build"
Dynamic: author
Dynamic: author-email
Dynamic: classifier
Dynamic: description
Dynamic: description-content-type
Dynamic: license
Dynamic: license-file
Dynamic: provides-extra
Dynamic: summary
